{"Scene_Delete": "{num} sahne silindi", "Scene_Add": "{num} sahne eklendi", "Video_Remove": "{num} video klip silindi", "update": "Güncelle", "title": "Güncelle", "defaultWorkset": "Varsayılan Çalışma Kümesi", "Furniture_Delete": "{num} model silindi", "noUpdate": "Güncelleme Yok", "Video_Add": "{num} video klip eklendi", "Furniture_Add": "{num} model eklendi", "WorkSet_RestoreBackUp": "Çalışma kümesi sürüm geri alımına uğradı.", "updateTitle": "Çalışma kümesini güncelle", "Furniture_Modify": "{num} model güncellendi"}
